README.rst
setup.py
summarization/__init__.py
summarization/summarizer.py
summarization.egg-info/PKG-INFO
summarization.egg-info/SOURCES.txt
summarization.egg-info/dependency_links.txt
summarization.egg-info/top_level.txt