Metadata-Version: 1.0
Name: summarization
Version: 0.0.1
Summary: Automatic summarization tools
Home-page: https://github.com/autosummarization/summarization
Author: taibai
Author-email: connection@autosummarization.com
License: MIT
Platform: UNKNOWN
